jalon
