Metadata-Version: 1.1
Name: jalon.connect
Version: 1.4
Summary: Un liaison avec Adobe Connect
Home-page: http://unice.fr
Author: Jerome Navarro, Bordonado Christophe - Université Nice Sophia Antipolis (uns) Service TICE
Author-email: tice@unice.fr
License: UNKNOWN
Platform: UNKNOWN
Classifier: Framework :: Plone
Classifier: Programming Language :: Python
